streamdeck_daemon/__init__.py
streamdeck_daemon/config/__init__.py
streamdeck_daemon/config/configuration.py
streamdeck_daemon/handlers/__init__.py
streamdeck_daemon/handlers/action_handler.py
streamdeck_daemon/handlers/key_handler.py
streamdeck_daemon/handlers/ui_handler.py
streamdeck_daemon/handlers/view_handler.py
streamdeck_daemon/logging/__init__.py
streamdeck_daemon/logging/logger.py
streamdeck_daemon/plugins/action.py
streamdeck_daemon/plugins/brightness.py
streamdeck_daemon/plugins/command.py
streamdeck_daemon/plugins/hue.py
streamdeck_daemon/plugins/launch.py
streamdeck_daemon/plugins/obs.py
streamdeck_daemon/plugins/page.py
streamdeck_daemon/plugins/shortcut.py
streamdeck_daemon/streamdeck.py
streamdeck_daemon-0.2.5.dist-info/entry_points.txt
streamdeck_daemon-0.2.5.dist-info/WHEEL
streamdeck_daemon-0.2.5.dist-info/METADATA
streamdeck_daemon-0.2.5.dist-info/RECORD
