Metadata-Version: 2.1
Name: streamdeck-daemon
Version: 0.2.5
Summary: A Simple daemon for controlling the Elgato Stremdeck devices
Author: Jesper Fussing Mørk
Author-email: jfm@moerks.dk
Requires-Python: >=3.6,<4.0
Classifier: Programming Language :: Python :: 3
Classifier: Programming Language :: Python :: 3.6
Classifier: Programming Language :: Python :: 3.7
Classifier: Programming Language :: Python :: 3.8
Classifier: Programming Language :: Python :: 3.9
Requires-Dist: phue (>=1.1,<2.0)
Requires-Dist: pillow (>=7.2.0,<8.0.0)
Requires-Dist: pluginbase (>=1.0.0,<2.0.0)
Requires-Dist: pyautogui (>=0.9.51,<0.10.0)
Requires-Dist: pyyaml (>=5.3.1,<6.0.0)
Requires-Dist: simpleobsws (>=0.0.7,<0.0.8)
Requires-Dist: streamdeck (>=0.8.2,<0.9.0)
Requires-Dist: xdg (>=4.0.1,<5.0.0)
